dense_basis/__init__.py
dense_basis/basic_fesc.py
dense_basis/gp_sfh.py
dense_basis/gp_sfh_old.py
dense_basis/mcmc.py
dense_basis/parallelization.py
dense_basis/plotter.py
dense_basis/pre_grid.py
dense_basis/priors.py
dense_basis/sed_fitter.py
dense_basis/tests.py
dense_basis/filters/filter_list.dat
dense_basis/filters/filter_list_cosmos.dat
dense_basis/filters/filter_list_cosmos_old.dat
dense_basis/filters/filter_list_egs.dat
dense_basis/filters/filter_list_goodsn.dat
dense_basis/filters/filter_list_goodss.dat
dense_basis/filters/filter_list_sloan_gri.dat
dense_basis/filters/filter_list_uds.dat
dense_basis/filters/filter_curves/cosmos/CFHT_iast.res
dense_basis/filters/filter_curves/cosmos/CFHT_uast.res
dense_basis/filters/filter_curves/cosmos/f10_Subaru_iccd.res
dense_basis/filters/filter_curves/cosmos/f11_Subaru_zccd.res
dense_basis/filters/filter_curves/cosmos/f12_ACS_f606w.res
dense_basis/filters/filter_curves/cosmos/f13_ACS_f814w.res
dense_basis/filters/filter_curves/cosmos/f14_WFC3_F125W.res
dense_basis/filters/filter_curves/cosmos/f15_WFC3_F160W.res
dense_basis/filters/filter_curves/cosmos/f16_Subaru_IAL484ccd.res
dense_basis/filters/filter_curves/cosmos/f17_Subaru_IAL527ccd.res
dense_basis/filters/filter_curves/cosmos/f18_Subaru_IAL624ccd.res
dense_basis/filters/filter_curves/cosmos/f19_Subaru_IAL679ccd.res
dense_basis/filters/filter_curves/cosmos/f1_CFHT_uccd.res
dense_basis/filters/filter_curves/cosmos/f20_Subaru_IAL738ccd.res
dense_basis/filters/filter_curves/cosmos/f21_Subaru_IAL767ccd.res
dense_basis/filters/filter_curves/cosmos/f22_Subaru_IAL427ccd.res
dense_basis/filters/filter_curves/cosmos/f23_Subaru_IAL464ccd.res
dense_basis/filters/filter_curves/cosmos/f24_Subaru_IAL505ccd.res
dense_basis/filters/filter_curves/cosmos/f25_Subaru_IAL574ccd.res
dense_basis/filters/filter_curves/cosmos/f26_Subaru_IAL709ccd.res
dense_basis/filters/filter_curves/cosmos/f27_Subaru_IAL827ccd.res
dense_basis/filters/filter_curves/cosmos/f28_Subaru_NB711ccd.res
dense_basis-0.1.9.dist-info/LICENSE
dense_basis-0.1.9.dist-info/METADATA
dense_basis-0.1.9.dist-info/WHEEL
dense_basis-0.1.9.dist-info/top_level.txt
dense_basis-0.1.9.dist-info/RECORD
