Metadata-Version: 2.1
Name: dense-basis
Version: 0.1.9
Summary: SED fitting with non-parametric star formation histories
Home-page: https://github.com/kartheikiyer/dense_basis
Author: Kartheik Iyer
Author-email: kartheik.iyer@dunlap.utoronto.ca
License: UNKNOWN
Platform: UNKNOWN
Classifier: Development Status :: 4 - Beta
Classifier: License :: OSI Approved :: MIT License
Classifier: Intended Audience :: Developers
Classifier: Intended Audience :: Science/Research
Classifier: Operating System :: OS Independent
Classifier: Programming Language :: Python :: 3.8
License-File: LICENSE
Requires-Dist: george
Requires-Dist: corner
Requires-Dist: hickle
Requires-Dist: schwimmbad
